fijitools/__init__.py
fijitools/helpers/__init__.py
fijitools/helpers/coordinate.py
fijitools/helpers/data_structures.py
fijitools/helpers/decorators.py
fijitools/helpers/iteration.py
fijitools/io/__init__.py
fijitools/io/path.py
fijitools/io/csv/__init__.py
fijitools/io/csv/csv_reader.py
fijitools/io/roi/__init__.py
fijitools/io/roi/old_stuff.py
fijitools/io/roi/roi_objects.py
fijitools/io/roi/roi_read.py
fijitools/io/roi/roi_write.py
fijitools/test/__init__.py
fijitools/test/run_tests.py
fijitools/test/test_coordinate.py
fijitools/test/test_data_structures.py
fijitools/test/test_pathfinder.py
fijitools/test/test_roi_reader.py
fijitools/test/test_roi_writer.py
fijitools/test/data/ovals.zip
fijitools/test/data/rectangles.zip
fijitools/test/data/test_image.tif
fijitools-0.2.dist-info/METADATA
fijitools-0.2.dist-info/RECORD
fijitools-0.2.dist-info/WHEEL
fijitools-0.2.dist-info/top_level.txt
