Metadata-Version: 2.1
Name: fijitools
Version: 0.2
Summary: UNKNOWN
Home-page: https://github.com/mistervladimir/fijitools
Author: Vladimir Shteyn
Author-email: vladimir.shteyn@googlemail.com
License: GNUv3
Download-URL: https://github.com/mistervladimir/fijitools/archive/0.2.tar.gz
Platform: UNKNOWN
Classifier: Intended Audience :: Science/Research
Classifier: Programming Language :: Python :: 3.6
Requires-Python: >=3.6
Requires-Dist: numpy
Requires-Dist: pyqt5
Requires-Dist: h5py
Requires-Dist: addict
Requires-Dist: pandas
Requires-Dist: six
Requires-Dist: pyyaml
